python2wb/__init__.py
python2wb/mqtt.py
python2wb-0.2.4.dist-info/LICENSE
python2wb-0.2.4.dist-info/METADATA
python2wb-0.2.4.dist-info/WHEEL
python2wb-0.2.4.dist-info/RECORD
