Metadata-Version: 2.1
Name: python2wb
Version: 0.2.4
Summary: Module for Python integration with Wiren Board MQTT
Author: Alexander Degtyarev
Author-email: adegtyarev.ap@gmail.com
Requires-Python: >=3.8,<4.0
Classifier: Programming Language :: Python :: 3
Classifier: Programming Language :: Python :: 3.8
Classifier: Programming Language :: Python :: 3.9
Classifier: Programming Language :: Python :: 3.10
Classifier: Programming Language :: Python :: 3.11
Classifier: Programming Language :: Python :: 3.12
Classifier: Programming Language :: Python :: 3.13
Requires-Dist: paho-mqtt (>=1.6,<2.0)
